e2me/__init__.py
e2me/api.py
e2me/e2me.toml
e2me/email_server.py
e2me/main.py
e2me/pop3.py
e2me/receive_email.py
e2me/send_email.py
e2me-0.0.10.dist-info/entry_points.txt
e2me-0.0.10.dist-info/LICENSE
e2me-0.0.10.dist-info/METADATA
e2me-0.0.10.dist-info/WHEEL
e2me-0.0.10.dist-info/RECORD
