Metadata-Version: 2.1
Name: e2me
Version: 0.0.10
Summary: 不知道什么时候跑完程序?发一封邮件吧
License: MIT
Author: luzhixing12345
Author-email: luzhixing12345@163.com
Requires-Python: >=3.6,<4.0
Classifier: License :: OSI Approved :: MIT License
Classifier: Programming Language :: Python :: 3
Classifier: Programming Language :: Python :: 3.6
Classifier: Programming Language :: Python :: 3.7
Classifier: Programming Language :: Python :: 3.8
Classifier: Programming Language :: Python :: 3.9
Classifier: Programming Language :: Python :: 3.10
Classifier: Programming Language :: Python :: 3.11
Requires-Dist: arrow
Requires-Dist: chardet
Requires-Dist: toml
